_ahlbatross_version.py
ahlbatross/__init__.py
ahlbatross/logger.ini
ahlbatross/logger.py
ahlbatross/main.py
ahlbatross/py.typed
ahlbatross/core/__init__.py
ahlbatross/core/ahb_comparison.py
ahlbatross/core/ahb_multicomparison.py
ahlbatross/core/ahb_processing.py
ahlbatross/enums/__init__.py
ahlbatross/enums/diff_types.py
ahlbatross/formats/__init__.py
ahlbatross/formats/csv.py
ahlbatross/formats/xlsx.py
ahlbatross/models/__init__.py
ahlbatross/models/ahb.py
ahlbatross/utils/__init__.py
ahlbatross/utils/string_formatting.py
ahlbatross/utils/xlsx_formatting.py
ahlbatross-0.2.0.dist-info/METADATA
ahlbatross-0.2.0.dist-info/WHEEL
ahlbatross-0.2.0.dist-info/entry_points.txt
ahlbatross-0.2.0.dist-info/licenses/LICENSE
ahlbatross-0.2.0.dist-info/RECORD
