Metadata-Version: 2.4
Name: ahlbatross
Version: 0.2.0
Summary: Tool for comparing and visualizing changes between AHB documents across different format version releases.
Project-URL: Changelog, https://github.com/Hochfrequenz/ahlbatross/releases
Project-URL: Homepage, https://github.com/Hochfrequenz/ahlbatross
Author-email: Hochfrequenz Unternehmensberatung GmbH <info@hochfrequenz.de>
License: MIT
License-File: LICENSE
Keywords: ahb
Classifier: Development Status :: 4 - Beta
Classifier: Environment :: Console
Classifier: Intended Audience :: Developers
Classifier: License :: OSI Approved :: MIT License
Classifier: Operating System :: OS Independent
Classifier: Programming Language :: Python
Classifier: Programming Language :: Python :: 3 :: Only
Classifier: Programming Language :: Python :: 3.11
Classifier: Programming Language :: Python :: 3.12
Classifier: Programming Language :: Python :: 3.13
Requires-Python: >=3.11
Requires-Dist: efoli>=1.4.0
Requires-Dist: kohlrahbi>=1.11.2
Requires-Dist: pydantic>=2.10.6
Requires-Dist: typer
Requires-Dist: xlsxwriter>=3.2.0
Provides-Extra: coverage
Requires-Dist: coverage==7.6.12; extra == 'coverage'
Provides-Extra: dev
Requires-Dist: pip-tools; extra == 'dev'
Provides-Extra: formatting
Requires-Dist: black==25.1.0; extra == 'formatting'
Requires-Dist: isort==6.0.0; extra == 'formatting'
Provides-Extra: linting
Requires-Dist: pylint==3.3.4; extra == 'linting'
Provides-Extra: packaging
Requires-Dist: build==1.2.2.post1; extra == 'packaging'
Requires-Dist: twine==6.1.0; extra == 'packaging'
Provides-Extra: spell-check
Requires-Dist: codespell==2.4.1; extra == 'spell-check'
Provides-Extra: tests
Requires-Dist: pytest==8.3.4; extra == 'tests'
Provides-Extra: type-check
Requires-Dist: mypy==1.15.0; extra == 'type-check'
